ocr_my_mess-0.3.16.dist-info/licenses/LICENSE
pdf_pipeline/__init__.py
pdf_pipeline/cli.py
pdf_pipeline/convert.py
pdf_pipeline/gui.py
pdf_pipeline/main.py
pdf_pipeline/merge.py
pdf_pipeline/utils.py
ocr_my_mess-0.3.16.dist-info/METADATA
ocr_my_mess-0.3.16.dist-info/WHEEL
ocr_my_mess-0.3.16.dist-info/entry_points.txt
ocr_my_mess-0.3.16.dist-info/top_level.txt
ocr_my_mess-0.3.16.dist-info/RECORD
