Metadata-Version: 2.4
Name: ocr-my-mess
Version: 0.3.16
Summary: A PDF pipeline to convert, OCR, and merge documents.
Project-URL: Homepage, https://github.com/example/ocr-my-mess
Project-URL: Bug Tracker, https://github.com/example/ocr-my-mess/issues
Classifier: Programming Language :: Python :: 3
Classifier: License :: OSI Approved :: MIT License
Classifier: Operating System :: OS Independent
Requires-Python: >=3.7
License-File: LICENSE
Requires-Dist: rich>=13.0.0
Requires-Dist: typer[all]>=0.9.0
Requires-Dist: pypdf>=3.0.0
Requires-Dist: ttkbootstrap>=1.10.1
Requires-Dist: ocrmypdf
Provides-Extra: dev
Requires-Dist: pymupdf; extra == "dev"
Requires-Dist: ruff; extra == "dev"
Requires-Dist: pytest; extra == "dev"
Requires-Dist: pyinstaller; extra == "dev"
Requires-Dist: twine; extra == "dev"
Dynamic: license-file
